loader.py
wg_load/__init__.py
wg_load/data_load.py
wg_load/load_ops.py
zhuque_dataloader-0.3.13.dist-info/METADATA
zhuque_dataloader-0.3.13.dist-info/WHEEL
zhuque_dataloader-0.3.13.dist-info/top_level.txt
zhuque_dataloader-0.3.13.dist-info/RECORD
