Metadata-Version: 2.1
Name: zhuque-dataloader
Version: 0.3.13
Summary: zhuque graph platform dataloader component
Author: yanrisheng
Author-email: yanrs@zhejianglab.com
License: GPL 3.0
